garminexport/__init__.py
garminexport/authenticator.py
garminexport/backup.py
garminexport/garminclient.py
garminexport/incremental_backup.py
garminexport/logging_config.py
garminexport/retryer.py
garminexport/token_store.py
garminexport/cli/__init__.py
garminexport/cli/backup.py
garminexport/cli/get_activity.py
garminexport/cli/upload_activity.py
garminexport-0.7.1.dist-info/LICENSE
garminexport-0.7.1.dist-info/METADATA
garminexport-0.7.1.dist-info/WHEEL
garminexport-0.7.1.dist-info/entry_points.txt
garminexport-0.7.1.dist-info/top_level.txt
garminexport-0.7.1.dist-info/zip-safe
garminexport-0.7.1.dist-info/RECORD
