Metadata-Version: 2.1
Name: garminexport
Version: 0.7.1
Summary: Garmin Connect activity exporter and backup tool
Home-page: https://github.com/petergardfjall/garminexport
Author: Peter Gardfjäll
Author-email: peter.gardfjall.work@gmail.com
License: Apache-2.0
Project-URL: Source, https://github.com/petergardfjall/garminexport.git
Project-URL: Tracker, https://github.com/petergardfjall/garminexport/issues
Keywords: garmin,export,backup
Classifier: Development Status :: 4 - Beta
Classifier: Intended Audience :: Developers
Classifier: Intended Audience :: End Users/Desktop
Classifier: Intended Audience :: Developers
Classifier: Natural Language :: English
Classifier: License :: OSI Approved :: Apache Software License
Classifier: Programming Language :: Python :: 3
Classifier: Programming Language :: Python :: 3.10
Classifier: Programming Language :: Python :: 3.11
Classifier: Programming Language :: Python :: 3.12
Classifier: Programming Language :: Python :: 3.13
Classifier: Programming Language :: Python :: 3.14
Requires-Python: >=3.10
License-File: LICENSE
Requires-Dist: requests<3,>=2.0
Requires-Dist: garth<0.6.0,>=0.5.21
Requires-Dist: python-dateutil~=2.4
Provides-Extra: test
Requires-Dist: pytest~=7.3; extra == "test"
Requires-Dist: pytest-cov~=4.0; extra == "test"
